{
  "mqAddress": {
    "label": "MQ服务端地址",
    "placeholder": "192.168.28.202:9092"
  },
  "topic": {
    "label": "主题",
    "placeholder": "test-topic"
  },
  "groupId": {
    "label": "消费端ID",
    "placeholder": "consume-group-id"
  },
  "offsetResetStrategy": {
    "label": "偏移量策略",
    "enum": [
      {
        "label": "Earliest",
        "val": "earliest"
      },
      {
        "label": "Latest",
        "val": "latest"
      },
      {
        "label": "None",
        "val": "none"
      }
    ]
  }
}