<?xml version="1.0" encoding="UTF-8"?>
<!DOCTYPE mapper PUBLIC "-//mybatis.org//DTD Mapper 3.0//EN" "http://mybatis.org/dtd/mybatis-3-mapper.dtd">
<mapper namespace="com.alibaba.tesla.appmanager.dynamicscript.repository.mapper.DynamicScriptDOMapper">
  <resultMap id="BaseResultMap" type="com.alibaba.tesla.appmanager.dynamicscript.repository.domain.DynamicScriptDO">
    <!--@mbg.generated-->
    <!--@Table am_dynamic_script-->
    <id column="id" jdbcType="BIGINT" property="id" />
    <result column="name" jdbcType="VARCHAR" property="name" />
    <result column="current_revision" jdbcType="INTEGER" property="currentRevision" />
    <result column="gmt_create" jdbcType="TIMESTAMP" property="gmtCreate" />
    <result column="gmt_modified" jdbcType="TIMESTAMP" property="gmtModified" />
    <result column="kind" jdbcType="VARCHAR" property="kind" />
  </resultMap>
  <resultMap extends="BaseResultMap" id="ResultMapWithBLOBs" type="com.alibaba.tesla.appmanager.dynamicscript.repository.domain.DynamicScriptDO">
    <!--@mbg.generated-->
    <!--@Table am_dynamic_script-->
    <result column="code" jdbcType="LONGVARCHAR" property="code" />
  </resultMap>
  <sql id="Example_Where_Clause">
    <!--@mbg.generated-->
    <where>
      <foreach collection="oredCriteria" item="criteria" separator="or">
        <if test="criteria.valid">
          <trim prefix="(" prefixOverrides="and" suffix=")">
            <foreach collection="criteria.criteria" item="criterion">
              <choose>
                <when test="criterion.noValue">
                  and ${criterion.condition}
                </when>
                <when test="criterion.singleValue">
                  and ${criterion.condition} #{criterion.value}
                </when>
                <when test="criterion.betweenValue">
                  and ${criterion.condition} #{criterion.value} and #{criterion.secondValue}
                </when>
                <when test="criterion.listValue">
                  and ${criterion.condition}
                  <foreach close=")" collection="criterion.value" item="listItem" open="(" separator=",">
                    #{listItem}
                  </foreach>
                </when>
              </choose>
            </foreach>
          </trim>
        </if>
      </foreach>
    </where>
  </sql>
  <sql id="Update_By_Example_Where_Clause">
    <!--@mbg.generated-->
    <where>
      <foreach collection="example.oredCriteria" item="criteria" separator="or">
        <if test="criteria.valid">
          <trim prefix="(" prefixOverrides="and" suffix=")">
            <foreach collection="criteria.criteria" item="criterion">
              <choose>
                <when test="criterion.noValue">
                  and ${criterion.condition}
                </when>
                <when test="criterion.singleValue">
                  and ${criterion.condition} #{criterion.value}
                </when>
                <when test="criterion.betweenValue">
                  and ${criterion.condition} #{criterion.value} and #{criterion.secondValue}
                </when>
                <when test="criterion.listValue">
                  and ${criterion.condition}
                  <foreach close=")" collection="criterion.value" item="listItem" open="(" separator=",">
                    #{listItem}
                  </foreach>
                </when>
              </choose>
            </foreach>
          </trim>
        </if>
      </foreach>
    </where>
  </sql>
  <sql id="Base_Column_List">
    <!--@mbg.generated-->
    id, `name`, current_revision, gmt_create, gmt_modified, kind
  </sql>
  <sql id="Blob_Column_List">
    <!--@mbg.generated-->
    code
  </sql>
  <select id="selectByExampleWithBLOBs" parameterType="com.alibaba.tesla.appmanager.dynamicscript.repository.domain.DynamicScriptDOExample" resultMap="ResultMapWithBLOBs">
    <!--@mbg.generated-->
    select
    <if test="distinct">
      distinct
    </if>
    <include refid="Base_Column_List" />
    ,
    <include refid="Blob_Column_List" />
    from am_dynamic_script
    <if test="_parameter != null">
      <include refid="Example_Where_Clause" />
    </if>
    order by id desc
  </select>
  <select id="selectByExample" parameterType="com.alibaba.tesla.appmanager.dynamicscript.repository.domain.DynamicScriptDOExample" resultMap="BaseResultMap">
    <!--@mbg.generated-->
    select
    <if test="distinct">
      distinct
    </if>
    <include refid="Base_Column_List" />
    from am_dynamic_script
    <if test="_parameter != null">
      <include refid="Example_Where_Clause" />
    </if>
    order by id desc
  </select>
  <select id="selectByPrimaryKey" parameterType="java.lang.Long" resultMap="ResultMapWithBLOBs">
    <!--@mbg.generated-->
    select 
    <include refid="Base_Column_List" />
    ,
    <include refid="Blob_Column_List" />
    from am_dynamic_script
    where id = #{id,jdbcType=BIGINT}
  </select>
  <delete id="deleteByPrimaryKey" parameterType="java.lang.Long">
    <!--@mbg.generated-->
    delete from am_dynamic_script
    where id = #{id,jdbcType=BIGINT}
  </delete>
  <delete id="deleteByExample" parameterType="com.alibaba.tesla.appmanager.dynamicscript.repository.domain.DynamicScriptDOExample">
    <!--@mbg.generated-->
    delete from am_dynamic_script
    <if test="_parameter != null">
      <include refid="Example_Where_Clause" />
    </if>
  </delete>
  <insert id="insert" keyColumn="id" keyProperty="id" parameterType="com.alibaba.tesla.appmanager.dynamicscript.repository.domain.DynamicScriptDO" useGeneratedKeys="true">
    <!--@mbg.generated-->
    insert into am_dynamic_script (`name`, current_revision, gmt_create, 
      gmt_modified, kind, code
      )
    values (#{name,jdbcType=VARCHAR}, #{currentRevision,jdbcType=INTEGER}, #{gmtCreate,jdbcType=TIMESTAMP}, 
      #{gmtModified,jdbcType=TIMESTAMP}, #{kind,jdbcType=VARCHAR}, #{code,jdbcType=LONGVARCHAR}
      )
  </insert>
  <insert id="insertSelective" keyColumn="id" keyProperty="id" parameterType="com.alibaba.tesla.appmanager.dynamicscript.repository.domain.DynamicScriptDO" useGeneratedKeys="true">
    <!--@mbg.generated-->
    insert into am_dynamic_script
    <trim prefix="(" suffix=")" suffixOverrides=",">
      <if test="name != null">
        `name`,
      </if>
      <if test="currentRevision != null">
        current_revision,
      </if>
      <if test="gmtCreate != null">
        gmt_create,
      </if>
      <if test="gmtModified != null">
        gmt_modified,
      </if>
      <if test="kind != null">
        kind,
      </if>
      <if test="code != null">
        code,
      </if>
    </trim>
    <trim prefix="values (" suffix=")" suffixOverrides=",">
      <if test="name != null">
        #{name,jdbcType=VARCHAR},
      </if>
      <if test="currentRevision != null">
        #{currentRevision,jdbcType=INTEGER},
      </if>
      <if test="gmtCreate != null">
        #{gmtCreate,jdbcType=TIMESTAMP},
      </if>
      <if test="gmtModified != null">
        #{gmtModified,jdbcType=TIMESTAMP},
      </if>
      <if test="kind != null">
        #{kind,jdbcType=VARCHAR},
      </if>
      <if test="code != null">
        #{code,jdbcType=LONGVARCHAR},
      </if>
    </trim>
  </insert>
  <select id="countByExample" parameterType="com.alibaba.tesla.appmanager.dynamicscript.repository.domain.DynamicScriptDOExample" resultType="java.lang.Long">
    <!--@mbg.generated-->
    select count(*) from am_dynamic_script
    <if test="_parameter != null">
      <include refid="Example_Where_Clause" />
    </if>
  </select>
  <update id="updateByExampleSelective" parameterType="map">
    <!--@mbg.generated-->
    update am_dynamic_script
    <set>
      <if test="record.id != null">
        id = #{record.id,jdbcType=BIGINT},
      </if>
      <if test="record.name != null">
        `name` = #{record.name,jdbcType=VARCHAR},
      </if>
      <if test="record.currentRevision != null">
        current_revision = #{record.currentRevision,jdbcType=INTEGER},
      </if>
      <if test="record.gmtCreate != null">
        gmt_create = #{record.gmtCreate,jdbcType=TIMESTAMP},
      </if>
      <if test="record.gmtModified != null">
        gmt_modified = #{record.gmtModified,jdbcType=TIMESTAMP},
      </if>
      <if test="record.kind != null">
        kind = #{record.kind,jdbcType=VARCHAR},
      </if>
      <if test="record.code != null">
        code = #{record.code,jdbcType=LONGVARCHAR},
      </if>
    </set>
    <if test="_parameter != null">
      <include refid="Update_By_Example_Where_Clause" />
    </if>
  </update>
  <update id="updateByExampleWithBLOBs" parameterType="map">
    <!--@mbg.generated-->
    update am_dynamic_script
    set id = #{record.id,jdbcType=BIGINT},
      `name` = #{record.name,jdbcType=VARCHAR},
      current_revision = #{record.currentRevision,jdbcType=INTEGER},
      gmt_create = #{record.gmtCreate,jdbcType=TIMESTAMP},
      gmt_modified = #{record.gmtModified,jdbcType=TIMESTAMP},
      kind = #{record.kind,jdbcType=VARCHAR},
      code = #{record.code,jdbcType=LONGVARCHAR}
    <if test="_parameter != null">
      <include refid="Update_By_Example_Where_Clause" />
    </if>
  </update>
  <update id="updateByExample" parameterType="map">
    <!--@mbg.generated-->
    update am_dynamic_script
    set id = #{record.id,jdbcType=BIGINT},
      `name` = #{record.name,jdbcType=VARCHAR},
      current_revision = #{record.currentRevision,jdbcType=INTEGER},
      gmt_create = #{record.gmtCreate,jdbcType=TIMESTAMP},
      gmt_modified = #{record.gmtModified,jdbcType=TIMESTAMP},
      kind = #{record.kind,jdbcType=VARCHAR}
    <if test="_parameter != null">
      <include refid="Update_By_Example_Where_Clause" />
    </if>
  </update>
  <update id="updateByPrimaryKeySelective" parameterType="com.alibaba.tesla.appmanager.dynamicscript.repository.domain.DynamicScriptDO">
    <!--@mbg.generated-->
    update am_dynamic_script
    <set>
      <if test="name != null">
        `name` = #{name,jdbcType=VARCHAR},
      </if>
      <if test="currentRevision != null">
        current_revision = #{currentRevision,jdbcType=INTEGER},
      </if>
      <if test="gmtCreate != null">
        gmt_create = #{gmtCreate,jdbcType=TIMESTAMP},
      </if>
      <if test="gmtModified != null">
        gmt_modified = #{gmtModified,jdbcType=TIMESTAMP},
      </if>
      <if test="kind != null">
        kind = #{kind,jdbcType=VARCHAR},
      </if>
      <if test="code != null">
        code = #{code,jdbcType=LONGVARCHAR},
      </if>
    </set>
    where id = #{id,jdbcType=BIGINT}
  </update>
  <update id="updateByPrimaryKeyWithBLOBs" parameterType="com.alibaba.tesla.appmanager.dynamicscript.repository.domain.DynamicScriptDO">
    <!--@mbg.generated-->
    update am_dynamic_script
    set `name` = #{name,jdbcType=VARCHAR},
      current_revision = #{currentRevision,jdbcType=INTEGER},
      gmt_create = #{gmtCreate,jdbcType=TIMESTAMP},
      gmt_modified = #{gmtModified,jdbcType=TIMESTAMP},
      kind = #{kind,jdbcType=VARCHAR},
      code = #{code,jdbcType=LONGVARCHAR}
    where id = #{id,jdbcType=BIGINT}
  </update>
  <update id="updateByPrimaryKey" parameterType="com.alibaba.tesla.appmanager.dynamicscript.repository.domain.DynamicScriptDO">
    <!--@mbg.generated-->
    update am_dynamic_script
    set `name` = #{name,jdbcType=VARCHAR},
      current_revision = #{currentRevision,jdbcType=INTEGER},
      gmt_create = #{gmtCreate,jdbcType=TIMESTAMP},
      gmt_modified = #{gmtModified,jdbcType=TIMESTAMP},
      kind = #{kind,jdbcType=VARCHAR}
    where id = #{id,jdbcType=BIGINT}
  </update>
</mapper>